eazeml/__init__.py
eazeml-0.0.7.dist-info/LICENSE.txt
eazeml-0.0.7.dist-info/METADATA
eazeml-0.0.7.dist-info/WHEEL
eazeml-0.0.7.dist-info/top_level.txt
eazeml-0.0.7.dist-info/RECORD
