Metadata-Version: 2.1
Name: eazeml
Version: 0.0.7
Summary: EazeML makes Task of Machine Learning and Data Science super easy.
Home-page: https://github.com/Chintan99/eazeml
Author: Chintan Chitroda
Author-email: chintanchitroda47@gmail.com
License: LICENSE.txt
Platform: UNKNOWN
Classifier: Programming Language :: Python :: 3
Classifier: License :: OSI Approved :: MIT License
Classifier: Operating System :: OS Independent
Requires-Dist: pandas
Requires-Dist: numpy
Requires-Dist: seaborn
Requires-Dist: matplotlib
Requires-Dist: plotly
Requires-Dist: sklearn
Requires-Dist: lightgbm
Requires-Dist: textblob
Requires-Dist: nltk
Requires-Dist: tqdm
Requires-Dist: flask
Requires-Dist: wordcloud
Requires-Dist: xgboost
Requires-Dist: cufflinks
Requires-Dist: catboost
